{
  "120363289207448746@g.us": {
    "isBanned": false,
    "welcome": false,
    "antiLink": false,
    "delete": true
  },
  "120363420980327478@g.us": {
    "isBanned": false,
    "welcome": false,
    "antiLink": false,
    "delete": true
  },
  "120363038763037721@g.us": {
    "isBanned": false,
    "welcome": false,
    "antiLink": false,
    "delete": true
  },
  "120363402954670642@g.us": {
    "isBanned": false,
    "welcome": false,
    "antiLink": false,
    "delete": true
  },
  "120363402823467991@g.us": {
    "isBanned": false,
    "welcome": false,
    "antiLink": false,
    "delete": true
  },
  "120363145689772156@g.us": {
    "isBanned": false,
    "welcome": false,
    "antiLink": false,
    "delete": true
  },
  "120363418197557310@g.us": {
    "isBanned": false,
    "welcome": false,
    "antiLink": false,
    "delete": true
  },
  "120363382148135664@g.us": {
    "isBanned": false,
    "welcome": false,
    "antiLink": false,
    "delete": true
  },
  "120363405585762478@g.us": {
    "isBanned": false,
    "welcome": false,
    "antiLink": false,
    "delete": true
  },
  "120363404378025483@g.us": {
    "isBanned": false,
    "welcome": false,
    "antiLink": false,
    "delete": true
  },
  "120363422269270861@g.us": {
    "isBanned": false,
    "welcome": false,
    "antiLink": false,
    "delete": true
  },
  "120363023958940214@g.us": {
    "isBanned": false,
    "welcome": false,
    "antiLink": false,
    "delete": true
  },
  "120363422500484010@g.us": {
    "isBanned": false,
    "welcome": false,
    "antiLink": false,
    "delete": true
  }
}